xingkong1/__init__.py
xingkong1/xingkong2/__init__.py
xingkong1/xingkong2/xingkong3/__init__.py
xingkong1/xingkong2/xingkong3/xingkong.py
xingkong-1.0.dist-info/METADATA
xingkong-1.0.dist-info/WHEEL
xingkong-1.0.dist-info/top_level.txt
xingkong-1.0.dist-info/RECORD
